dash_dock_view/DashDockLayout.py
dash_dock_view/DashGridLayout.py
dash_dock_view/DashPaneLayout.py
dash_dock_view/DashSplitLayout.py
dash_dock_view/__init__.py
dash_dock_view/_imports_.py
dash_dock_view/dash_dock_view.min.js
dash_dock_view/dash_dock_view.min.js.map
dash_dock_view/metadata.json
dash_dock_view/package-info.json
dash_dock_view-1.0.0.dist-info/LICENSE
dash_dock_view-1.0.0.dist-info/METADATA
dash_dock_view-1.0.0.dist-info/WHEEL
dash_dock_view-1.0.0.dist-info/top_level.txt
dash_dock_view-1.0.0.dist-info/RECORD
